<templateSet group="user">
  <template name="test" value="/** &#10; * @test&#10; */&#10;public function it_$NAME$(): void&#10;{&#10;    $END$&#10;}" description="Make a single test function" toReformat="true" toShortenFQNames="true">
    <variable name="NAME" expression="" defaultValue="" alwaysStopAt="true" />
    <context>
      <option name="PHP Class Member" value="true" />
    </context>
  </template>
  <template name="met" value="public function $NAME$()&#10;{&#10;    $END$&#10;}" description="Make a public class method" toReformat="true" toShortenFQNames="true">
    <variable name="NAME" expression="" defaultValue="" alwaysStopAt="true" />
    <context>
      <option name="PHP Class Member" value="true" />
    </context>
  </template>
  <template name="smet" value="public static function $NAME$()&#10;{&#10;    $END$&#10;}" description="Make a public static function" toReformat="true" toShortenFQNames="true">
    <variable name="NAME" expression="" defaultValue="" alwaysStopAt="true" />
    <context>
      <option name="PHP Class Member" value="true" />
    </context>
  </template>
  <template name="pmet" value="private function $NAME$()&#10;{&#10;    $END$&#10;}" description="Make a private class function" toReformat="true" toShortenFQNames="true">
    <variable name="NAME" expression="" defaultValue="" alwaysStopAt="true" />
    <context>
      <option name="PHP Class Member" value="true" />
    </context>
  </template>
</templateSet>